{
  "basics": {
    "name": "Joshua Sylvester",
    "label": "Cyber Security Researcher",
    "summary": "A motivated and hardworking researcher with a passion for artificial intelligence and cyber security. Experienced in reinforcement learning, cyber defence, and machine learning applications. Committed to advancing autonomous cyber defence through scalable reinforcement learning methods and the detection and mitigation of novel threats.",
    "location": {
      "address": "",
      "postalCode": "",
      "city": "Canterbury",
      "countryCode": "UK",
      "region": "Kent"
    },
    "profiles": []
  },
  "work": [
    {
      "name": "Along side the Alan Turing Institute",
      "position": "Cyber Security Researcher",
      "url": "",
      "startDate": "2025-07-14",
      "endDate": "",
      "summary": "Researching reinforcement learning for autonomous cyber defence."
    },
    {
      "name": "University of Kent",
      "position": "Graduate Teaching Assistant",
      "url": "https://www.kent.ac.uk/",
      "startDate": "2023-01-01",
      "endDate": "",
      "summary": "Lead instructor during practical sessions, responsible for grading, feedback, academic support, and facilitating student engagement.",
      "highlights": [
        "Led undergraduate computing classes.",
        "Prepared instructional materials and guided student projects."
      ]
    },
    {
      "name": "Orange Cyberdefense",
      "position": "Security Research Intern",
      "url": "https://orangecyberdefense.com/",
      "startDate": "2022-06-01",
      "endDate": "2022-12-01",
      "summary": "Applied machine learning to cybersecurity problems such as text classification and named-entity recognition. Automated data labelling and built containerised solutions for production.",
      "highlights": [
        "Developed web scrapers and automated labelling pipelines.",
        "Produced monthly and final-year security landscape reports."
      ]
    },
    {
      "name": "Tesco",
      "position": "Personal Shopper",
      "url": "",
      "startDate": "2019-01-01",
      "endDate": "2021-12-31",
      "summary": "Managed customer orders, ensured order accuracy, and maintained stock rotation and safety compliance.",
      "highlights": ["Trained new staff members in operational procedures."]
    },
    {
      "name": "Othello’s Restaurant",
      "position": "Waiter",
      "url": "",
      "startDate": "2017-01-01",
      "endDate": "2019-12-31",
      "summary": "Provided customer service in a fast-paced environment, handled transactions, and ensured hygiene standards.",
      "highlights": ["Developed strong teamwork and customer communication skills."]
    }
  ],
  "education": [
    {
      "endDate": "",
      "startDate": "2023-01-14",
      "institution": "University of Kent",
      "area": "Cyber Security and Artificial Intelligence",
      "studyType": "PhD (Ongoing)",
      "url": "https://www.kent.ac.uk/",
      "summary": "Working on autonomous cyber defence and reinforcement learning, with research published at IEEE CSR and collaboration with Dstl ARCD on 'Reward shaping for network defence based on reinforcement learning.'"
    },
    {
      "startDate": "2019-09-01",
      "endDate": "2022-06-01",
      "institution": "University of Kent",
      "area": "Computer Science",
      "studyType": "Bachelor’s Degree (Hons)",
      "score": "First Class",
      "url": "https://www.kent.ac.uk/",
      "summary": "Awarded for outstanding overall performance and best final-year project in the School of Computing."
    },
    {
      "endDate": "2019-06-01",
      "startDate": "2017-09-01",
      "institution": "East Norfolk Sixth Form College",
      "area": "A-Levels",
      "studyType": "Pre-University",
      "courses": ["Computer Science (B)", "Chemistry (A)", "Mathematics (B)"]
    },
    {
      "endDate": "2017-06-01",
      "startDate": "2015-09-01",
      "institution": "University Technical College Norfolk",
      "area": "General Education",
      "studyType": "GCSEs",
      "courses": [
        "Mathematics (8)",
        "Physics (A)",
        "Chemistry (A)",
        "Computer Science (B)",
        "Engineering (Pass)"
      ]
    }
  ],
  "awards": [
    {
      "title": "Outstanding Overall Performance in the School of Computing",
      "date": "2022-08-01",
      "awarder": "University of Kent",
      "summary": "Awarded to the highest performing student of the year for achieving the best overall marks in the degree programme."
    },
    {
      "title": "Best Final Year Computing Research Project award",
      "date": "2022-08-01",
      "awarder": "University of Kent",
      "summary": "Best Final Year Computing Research Project award, given to the student with the highest performing research project in the degree programme."
    },
    {
      "title": "Distinguished Paper Award",
      "date": "2025-09-25",
      "awarder": "ESORICS 2025 - AutonomousCyber 2025",
      "summary": "Received the Distinguished Paper Award at the AutonomousCyber 2025 workshop for outstanding research contribution to autonomous cyber defence."
    }
  ],
  "skills": [
    {
      "name": "Technical Skills",
      "icon": "fa-solid fa-hashtag",
      "keywords": [
        "Cyber Security",
        "Reinforcement Learning",
        "Artificial Intelligence",
        "Machine Learning",
        "Python",
        "Docker",
        "Data Analysis"
      ]
    },
    {
      "name": "Soft Skills",
      "icon": "fa-solid fa-hashtag",
      "keywords": [
        "Attention to Detail",
        "Creativity",
        "Organisation",
        "Training and Teaching",
        "Teamwork",
        "Time Management",
        "Communication"
      ]
    }
  ],
  "projects": [
    {
      "name": "Reward Shaping for Network Defence",
      "summary": "Collaborative research project with Dstl ARCD exploring reinforcement learning techniques for autonomous cyber defence agents.",
      "url": "",
      "highlights": [
        "Applied reinforcement learning to network defence tasks."
      ]
    }
  ],
  "interests": [
    {
      "name": "Hobbies",
      "icon": "fa-solid fa-hashtag",
      "keywords": ["Fishing", "Swimming", "Gym", "Reading", "Cooking"]
    }
  ]
}